pyjamf/__init__.py
pyjamf/builder/__init__.py
pyjamf/builder/classic/__init__.py
pyjamf/builder/classic/_advanced_computer_search_request_builder.py
pyjamf/builder/classic/_building_request_builder.py
pyjamf/builder/classic/_category_request_builder.py
pyjamf/builder/classic/_computer_group_id_request_builder.py
pyjamf/builder/classic/_computer_group_request_builder.py
pyjamf/builder/classic/_computer_id_request_builder.py
pyjamf/builder/classic/_computer_request_builder.py
pyjamf/builder/classic/_department_request_builder.py
pyjamf/builder/classic/_jamf_classic_request_builder.py
pyjamf/builder/pro/__init__.py
pyjamf/builder/pro/_advanced_mobile_device_searches_choices_request_builder.py
pyjamf/builder/pro/_advanced_mobile_device_searches_delete_multiple_request_builder.py
pyjamf/builder/pro/_advanced_mobile_device_searches_request_builder.py
pyjamf/builder/pro/_advanced_user_content_searches_request_builder.py
pyjamf/builder/pro/_app_dynamics_request_builder.py
pyjamf/builder/pro/_app_dynamics_script_configuration_request_builder.py
pyjamf/builder/pro/_buildings_delete_multiple_request_builder.py
pyjamf/builder/pro/_buildings_export_request_builder.py
pyjamf/builder/pro/_buildings_history_export_request_builder.py
pyjamf/builder/pro/_buildings_history_request_builder.py
pyjamf/builder/pro/_buildings_request_builder.py
pyjamf/builder/pro/_cache_settings_request_builder.py
pyjamf/builder/pro/_categories_delete_multiple_request_builder.py
pyjamf/builder/pro/_categories_request_builder.py
pyjamf/builder/pro/_classic_ldap_request_builder.py
pyjamf/builder/pro/_client_check_in_history_request_builder.py
pyjamf/builder/pro/_client_check_in_request_builder.py
pyjamf/builder/pro/_computer_groups_request_builder.py
pyjamf/builder/pro/_departmentsrequestbuilder.py
pyjamf/builder/pro/_jamf_pro_request_builder.py
pyjamf/builder/pro/_mobile_device_request_builder.py
pyjamf/builder/pro/_mobile_devices_collection_request_builder.py
pyjamf-0.1.0.dist-info/LICENSE
pyjamf-0.1.0.dist-info/WHEEL
pyjamf-0.1.0.dist-info/METADATA
pyjamf-0.1.0.dist-info/RECORD
